sapid/__init__.py
sapid/bot.py
sapid/comment.py
sapid/enums.py
sapid/errors.py
sapid/http.py
sapid/installation.py
sapid/issue.py
sapid/repository.py
sapid/server.py
sapid/state.py
sapid/user.py
sapid/utils.py
sapid/types/comment.py
sapid/types/installation.py
sapid/types/issue.py
sapid/types/repository.py
sapid/types/user.py
sapid-1.0.0a0.dist-info/METADATA
sapid-1.0.0a0.dist-info/WHEEL
sapid-1.0.0a0.dist-info/top_level.txt
sapid-1.0.0a0.dist-info/RECORD
