Metadata-Version: 2.1
Name: sapid
Version: 1.0.0a0
Summary: A robust asynchronous framework for building scalable GitHub Applications.
Home-page: UNKNOWN
Author: justanotherbyte
License: MIT
Platform: UNKNOWN
Classifier: Development Status :: 5 - Production/Stable
Classifier: License :: OSI Approved :: MIT License
Classifier: Intended Audience :: Developers
Classifier: Natural Language :: English
Classifier: Operating System :: OS Independent
Classifier: Programming Language :: Python :: 3.8
Classifier: Programming Language :: Python :: 3.9
Classifier: Topic :: Internet
Classifier: Topic :: Software Development :: Libraries
Classifier: Topic :: Software Development :: Libraries :: Python Modules
Classifier: Topic :: Utilities
Classifier: Typing :: Typed
Requires-Dist: aiohttp
Requires-Dist: pyjwt[crypto]
Provides-Extra: proxy-support
Requires-Dist: aiohttp-remotes ; extra == 'proxy-support'
